[
  {
    "line": 3,
    "elements": [
      {
        "start_timestamp": "2021-03-06T00:01:49.034Z",
        "before": [
          {
            "result": {
              "status": "passed"
            },
            "match": {
              "location": "com.taskCR.step_definitions.Hooks.setUp()"
            }
          }
        ],
        "line": 14,
        "name": "User is able to find the desire shop",
        "description": "",
        "id": "search-a-shop;user-is-able-to-find-the-desire-shop;;2",
        "after": [
          {
            "result": {
              "duration": 609376900,
              "status": "passed"
            },
            "match": {
              "location": "com.taskCR.step_definitions.Hooks.tearDown(io.cucumber.java.Scenario)"
            }
          }
        ],
        "type": "scenario",
        "keyword": "Scenario Outline",
        "steps": [
          {
            "result": {
              "duration": 7537120000,
              "status": "passed"
            },
            "line": 7,
            "name": "User is on the Shop search results page",
            "match": {
              "location": "com.taskCR.step_definitions.searchShopResult_StepDefs.user_is_on_the_Shop_search_results_page()"
            },
            "keyword": "Given "
          },
          {
            "result": {
              "duration": 3049056800,
              "status": "passed"
            },
            "line": 8,
            "name": "User enter a \"London\"",
            "match": {
              "arguments": [
                {
                  "val": "\"London\"",
                  "offset": 13
                }
              ],
              "location": "com.taskCR.step_definitions.searchShopResult_StepDefs.user_enter_a(java.lang.String)"
            },
            "keyword": "When "
          },
          {
            "result": {
              "duration": 299201200,
              "status": "passed"
            },
            "line": 9,
            "name": "User click the find a shop button",
            "match": {
              "location": "com.taskCR.step_definitions.searchShopResult_StepDefs.user_click_the_find_a_shop_button()"
            },
            "keyword": "And "
          },
          {
            "result": {
              "duration": 191484600,
              "status": "passed"
            },
            "line": 10,
            "name": "User is able to see a shop in the desired location",
            "match": {
              "location": "com.taskCR.step_definitions.searchShopResult_StepDefs.user_is_able_to_see_a_shop_in_the_desired_location()"
            },
            "keyword": "Then "
          }
        ],
        "tags": [
          {
            "name": "@wip"
          }
        ]
      },
      {
        "start_timestamp": "2021-03-06T00:02:00.769Z",
        "before": [
          {
            "result": {
              "status": "passed"
            },
            "match": {
              "location": "com.taskCR.step_definitions.Hooks.setUp()"
            }
          }
        ],
        "line": 15,
        "name": "User is able to find the desire shop",
        "description": "",
        "id": "search-a-shop;user-is-able-to-find-the-desire-shop;;3",
        "after": [
          {
            "result": {
              "duration": 605384800,
              "status": "passed"
            },
            "match": {
              "location": "com.taskCR.step_definitions.Hooks.tearDown(io.cucumber.java.Scenario)"
            }
          }
        ],
        "type": "scenario",
        "keyword": "Scenario Outline",
        "steps": [
          {
            "result": {
              "duration": 7691431900,
              "status": "passed"
            },
            "line": 7,
            "name": "User is on the Shop search results page",
            "match": {
              "location": "com.taskCR.step_definitions.searchShopResult_StepDefs.user_is_on_the_Shop_search_results_page()"
            },
            "keyword": "Given "
          },
          {
            "result": {
              "duration": 3045277500,
              "status": "passed"
            },
            "line": 8,
            "name": "User enter a \"Leeds\"",
            "match": {
              "arguments": [
                {
                  "val": "\"Leeds\"",
                  "offset": 13
                }
              ],
              "location": "com.taskCR.step_definitions.searchShopResult_StepDefs.user_enter_a(java.lang.String)"
            },
            "keyword": "When "
          },
          {
            "result": {
              "duration": 310169200,
              "status": "passed"
            },
            "line": 9,
            "name": "User click the find a shop button",
            "match": {
              "location": "com.taskCR.step_definitions.searchShopResult_StepDefs.user_click_the_find_a_shop_button()"
            },
            "keyword": "And "
          },
          {
            "result": {
              "duration": 146608600,
              "status": "passed"
            },
            "line": 10,
            "name": "User is able to see a shop in the desired location",
            "match": {
              "location": "com.taskCR.step_definitions.searchShopResult_StepDefs.user_is_able_to_see_a_shop_in_the_desired_location()"
            },
            "keyword": "Then "
          }
        ],
        "tags": [
          {
            "name": "@wip"
          }
        ]
      },
      {
        "start_timestamp": "2021-03-06T00:02:12.570Z",
        "before": [
          {
            "result": {
              "status": "passed"
            },
            "match": {
              "location": "com.taskCR.step_definitions.Hooks.setUp()"
            }
          }
        ],
        "line": 16,
        "name": "User is able to find the desire shop",
        "description": "",
        "id": "search-a-shop;user-is-able-to-find-the-desire-shop;;4",
        "after": [
          {
            "result": {
              "duration": 607374600,
              "status": "passed"
            },
            "match": {
              "location": "com.taskCR.step_definitions.Hooks.tearDown(io.cucumber.java.Scenario)"
            }
          }
        ],
        "type": "scenario",
        "keyword": "Scenario Outline",
        "steps": [
          {
            "result": {
              "duration": 6533778100,
              "status": "passed"
            },
            "line": 7,
            "name": "User is on the Shop search results page",
            "match": {
              "location": "com.taskCR.step_definitions.searchShopResult_StepDefs.user_is_on_the_Shop_search_results_page()"
            },
            "keyword": "Given "
          },
          {
            "result": {
              "duration": 3047850300,
              "status": "passed"
            },
            "line": 8,
            "name": "User enter a \"Cambridge\"",
            "match": {
              "arguments": [
                {
                  "val": "\"Cambridge\"",
                  "offset": 13
                }
              ],
              "location": "com.taskCR.step_definitions.searchShopResult_StepDefs.user_enter_a(java.lang.String)"
            },
            "keyword": "When "
          },
          {
            "result": {
              "duration": 324134000,
              "status": "passed"
            },
            "line": 9,
            "name": "User click the find a shop button",
            "match": {
              "location": "com.taskCR.step_definitions.searchShopResult_StepDefs.user_click_the_find_a_shop_button()"
            },
            "keyword": "And "
          },
          {
            "result": {
              "duration": 200462900,
              "status": "passed"
            },
            "line": 10,
            "name": "User is able to see a shop in the desired location",
            "match": {
              "location": "com.taskCR.step_definitions.searchShopResult_StepDefs.user_is_able_to_see_a_shop_in_the_desired_location()"
            },
            "keyword": "Then "
          }
        ],
        "tags": [
          {
            "name": "@wip"
          }
        ]
      },
      {
        "start_timestamp": "2021-03-06T00:02:23.287Z",
        "before": [
          {
            "result": {
              "status": "passed"
            },
            "match": {
              "location": "com.taskCR.step_definitions.Hooks.setUp()"
            }
          }
        ],
        "line": 27,
        "name": "User is not able to find the desired shop",
        "description": "",
        "id": "search-a-shop;user-is-not-able-to-find-the-desired-shop;;2",
        "after": [
          {
            "result": {
              "duration": 606115100,
              "status": "passed"
            },
            "match": {
              "location": "com.taskCR.step_definitions.Hooks.tearDown(io.cucumber.java.Scenario)"
            }
          }
        ],
        "type": "scenario",
        "keyword": "Scenario Outline",
        "steps": [
          {
            "result": {
              "duration": 6752943400,
              "status": "passed"
            },
            "line": 20,
            "name": "User is on the Shop search results page",
            "match": {
              "location": "com.taskCR.step_definitions.searchShopResult_StepDefs.user_is_on_the_Shop_search_results_page()"
            },
            "keyword": "Given "
          },
          {
            "result": {
              "duration": 3043856800,
              "status": "passed"
            },
            "line": 21,
            "name": "User enter a \"Rome\"",
            "match": {
              "arguments": [
                {
                  "val": "\"Rome\"",
                  "offset": 13
                }
              ],
              "location": "com.taskCR.step_definitions.searchShopResult_StepDefs.user_enter_a(java.lang.String)"
            },
            "keyword": "When "
          },
          {
            "result": {
              "duration": 363029100,
              "status": "passed"
            },
            "line": 22,
            "name": "User click the find a shop button",
            "match": {
              "location": "com.taskCR.step_definitions.searchShopResult_StepDefs.user_click_the_find_a_shop_button()"
            },
            "keyword": "And "
          },
          {
            "result": {
              "duration": 195476100,
              "status": "passed"
            },
            "line": 23,
            "name": "User is not able to see a shop in the desired location",
            "match": {
              "location": "com.taskCR.step_definitions.searchShopResult_StepDefs.user_is_not_able_to_see_a_shop_in_the_desired_location()"
            },
            "keyword": "Then "
          }
        ],
        "tags": [
          {
            "name": "@wip"
          }
        ]
      },
      {
        "start_timestamp": "2021-03-06T00:02:34.254Z",
        "before": [
          {
            "result": {
              "status": "passed"
            },
            "match": {
              "location": "com.taskCR.step_definitions.Hooks.setUp()"
            }
          }
        ],
        "line": 28,
        "name": "User is not able to find the desired shop",
        "description": "",
        "id": "search-a-shop;user-is-not-able-to-find-the-desired-shop;;3",
        "after": [
          {
            "result": {
              "duration": 604753200,
              "status": "passed"
            },
            "match": {
              "location": "com.taskCR.step_definitions.Hooks.tearDown(io.cucumber.java.Scenario)"
            }
          }
        ],
        "type": "scenario",
        "keyword": "Scenario Outline",
        "steps": [
          {
            "result": {
              "duration": 7746503500,
              "status": "passed"
            },
            "line": 20,
            "name": "User is on the Shop search results page",
            "match": {
              "location": "com.taskCR.step_definitions.searchShopResult_StepDefs.user_is_on_the_Shop_search_results_page()"
            },
            "keyword": "Given "
          },
          {
            "result": {
              "duration": 3048975100,
              "status": "passed"
            },
            "line": 21,
            "name": "User enter a \"Chicago\"",
            "match": {
              "arguments": [
                {
                  "val": "\"Chicago\"",
                  "offset": 13
                }
              ],
              "location": "com.taskCR.step_definitions.searchShopResult_StepDefs.user_enter_a(java.lang.String)"
            },
            "keyword": "When "
          },
          {
            "result": {
              "duration": 2092405300,
              "status": "passed"
            },
            "line": 22,
            "name": "User click the find a shop button",
            "match": {
              "location": "com.taskCR.step_definitions.searchShopResult_StepDefs.user_click_the_find_a_shop_button()"
            },
            "keyword": "And "
          },
          {
            "result": {
              "duration": 139626400,
              "status": "passed"
            },
            "line": 23,
            "name": "User is not able to see a shop in the desired location",
            "match": {
              "location": "com.taskCR.step_definitions.searchShopResult_StepDefs.user_is_not_able_to_see_a_shop_in_the_desired_location()"
            },
            "keyword": "Then "
          }
        ],
        "tags": [
          {
            "name": "@wip"
          }
        ]
      },
      {
        "start_timestamp": "2021-03-06T00:02:47.890Z",
        "before": [
          {
            "result": {
              "duration": 997100,
              "status": "passed"
            },
            "match": {
              "location": "com.taskCR.step_definitions.Hooks.setUp()"
            }
          }
        ],
        "line": 29,
        "name": "User is not able to find the desired shop",
        "description": "",
        "id": "search-a-shop;user-is-not-able-to-find-the-desired-shop;;4",
        "after": [
          {
            "result": {
              "duration": 606377100,
              "status": "passed"
            },
            "match": {
              "location": "com.taskCR.step_definitions.Hooks.tearDown(io.cucumber.java.Scenario)"
            }
          }
        ],
        "type": "scenario",
        "keyword": "Scenario Outline",
        "steps": [
          {
            "result": {
              "duration": 7345158600,
              "status": "passed"
            },
            "line": 20,
            "name": "User is on the Shop search results page",
            "match": {
              "location": "com.taskCR.step_definitions.searchShopResult_StepDefs.user_is_on_the_Shop_search_results_page()"
            },
            "keyword": "Given "
          },
          {
            "result": {
              "duration": 3045855200,
              "status": "passed"
            },
            "line": 21,
            "name": "User enter a \"Paris\"",
            "match": {
              "arguments": [
                {
                  "val": "\"Paris\"",
                  "offset": 13
                }
              ],
              "location": "com.taskCR.step_definitions.searchShopResult_StepDefs.user_enter_a(java.lang.String)"
            },
            "keyword": "When "
          },
          {
            "result": {
              "duration": 426857100,
              "status": "passed"
            },
            "line": 22,
            "name": "User click the find a shop button",
            "match": {
              "location": "com.taskCR.step_definitions.searchShopResult_StepDefs.user_click_the_find_a_shop_button()"
            },
            "keyword": "And "
          },
          {
            "result": {
              "duration": 189493800,
              "status": "passed"
            },
            "line": 23,
            "name": "User is not able to see a shop in the desired location",
            "match": {
              "location": "com.taskCR.step_definitions.searchShopResult_StepDefs.user_is_not_able_to_see_a_shop_in_the_desired_location()"
            },
            "keyword": "Then "
          }
        ],
        "tags": [
          {
            "name": "@wip"
          }
        ]
      }
    ],
    "name": "Search a shop",
    "description": "",
    "id": "search-a-shop",
    "keyword": "Feature",
    "uri": "file:src/test/resources/features/searchShopResult.feature",
    "tags": [
      {
        "name": "@wip",
        "type": "Tag",
        "location": {
          "line": 2,
          "column": 1
        }
      }
    ]
  }
]